asyncificate/__init__.py
asyncificate-1.0.0.dist-info/METADATA
asyncificate-1.0.0.dist-info/WHEEL
asyncificate-1.0.0.dist-info/RECORD
