Metadata-Version: 2.1
Name: asyncificate
Version: 1.0.0
Summary: Simple library with decorators to make sync function async
License: MIT
Author: Xenely
Author-email: amaryatkin@vk.com
Requires-Python: >=3.10,<4.0
Classifier: License :: OSI Approved :: MIT License
Classifier: Programming Language :: Python :: 3
Classifier: Programming Language :: Python :: 3.10
Classifier: Programming Language :: Python :: 3.11
Classifier: Programming Language :: Python :: 3.12
